duckalog/__init__.py
duckalog/benchmarks.py
duckalog/cli.py
duckalog/config_init.py
duckalog/connection.py
duckalog/engine.py
duckalog/errors.py
duckalog/logging_utils.py
duckalog/performance.py
duckalog/py.typed
duckalog/python_api.py
duckalog/remote_config.py
duckalog/secret_types.py
duckalog/sql_file_loader.py
duckalog/sql_generation.py
duckalog/sql_utils.py
duckalog/config/__init__.py
duckalog/config/api.py
duckalog/config/interpolation.py
duckalog/config/loader.py
duckalog/config/models.py
duckalog/config/validators.py
duckalog/config/loading/__init__.py
duckalog/config/loading/base.py
duckalog/config/loading/file.py
duckalog/config/loading/remote.py
duckalog/config/loading/sql.py
duckalog/config/resolution/__init__.py
duckalog/config/resolution/base.py
duckalog/config/resolution/env.py
duckalog/config/resolution/imports.py
duckalog/config/security/__init__.py
duckalog/config/security/base.py
duckalog/config/security/path.py
duckalog/dashboard/__init__.py
duckalog/dashboard/app.py
duckalog/dashboard/state.py
duckalog/dashboard/components/__init__.py
duckalog/dashboard/components/layout.py
duckalog/dashboard/routes/__init__.py
duckalog/dashboard/routes/home.py
duckalog/dashboard/routes/query.py
duckalog/dashboard/routes/views.py
duckalog-0.5.0.dist-info/licenses/LICENSE
duckalog-0.5.0.dist-info/METADATA
duckalog-0.5.0.dist-info/WHEEL
duckalog-0.5.0.dist-info/entry_points.txt
duckalog-0.5.0.dist-info/top_level.txt
duckalog-0.5.0.dist-info/RECORD
