Metadata-Version: 2.4
Name: duckalog
Version: 0.5.0
Summary: Python library and CLI to build DuckDB catalogs from declarative YAML/JSON configs
Author-email: legout <ligno.blades@gmail.com>
Project-URL: Homepage, https://legout.github.io/duckalog/
Project-URL: Repository, https://github.com/legout/duckalog
Project-URL: Documentation, https://legout.github.io/duckalog/
Project-URL: Changelog, https://github.com/legout/duckalog/blob/main/CHANGELOG.md
Project-URL: Issues, https://github.com/legout/duckalog/issues
Project-URL: Discussions, https://github.com/legout/duckalog/discussions
Project-URL: Security, https://github.com/legout/duckalog/blob/main/SECURITY.md
Project-URL: CI, https://github.com/legout/duckalog/actions
Keywords: duckdb,catalog,yaml,json,data-engineering,database,views,configuration,cli,python,etl,analytics
Classifier: Development Status :: 4 - Beta
Classifier: Intended Audience :: Developers
Classifier: Intended Audience :: Information Technology
Classifier: License :: OSI Approved :: MIT License
Classifier: Operating System :: OS Independent
Classifier: Programming Language :: Python :: 3
Classifier: Programming Language :: Python :: 3.12
Classifier: Programming Language :: Python :: 3.13
Classifier: Programming Language :: Python :: 3 :: Only
Classifier: Topic :: Database
Classifier: Topic :: Database :: Database Engines/Servers
Classifier: Topic :: Software Development :: Libraries :: Python Modules
Classifier: Topic :: System :: Systems Administration
Classifier: Topic :: Utilities
Classifier: Topic :: Scientific/Engineering
Classifier: Natural Language :: English
Classifier: Environment :: Console
Classifier: Environment :: Web Environment
Requires-Python: >=3.12
License-File: LICENSE
Requires-Dist: duckdb>=0.8.0
Requires-Dist: pyyaml>=6.0
Requires-Dist: pydantic>=2.0.0
Requires-Dist: click>=8.0.0
Requires-Dist: loguru>=0.7.0
Requires-Dist: typer>=0.20.0
Requires-Dist: datastar-py>=0.7.0
Requires-Dist: python-dotenv>=1.0.0
Provides-Extra: ui
Requires-Dist: litestar>=2.0.0; extra == "ui"
Requires-Dist: htpy>=0.1.0; extra == "ui"
Requires-Dist: datastar-py>=0.7.0; extra == "ui"
Requires-Dist: uvicorn[standard]>=0.24.0; extra == "ui"
Requires-Dist: python-multipart>=0.0.20; extra == "ui"
Requires-Dist: msgspec>=0.18.0; extra == "ui"
Requires-Dist: sniffio>=1.3.0; extra == "ui"
Provides-Extra: remote
Requires-Dist: fsspec>=2023.6.0; extra == "remote"
Requires-Dist: requests>=2.28.0; extra == "remote"
Provides-Extra: remote-s3
Requires-Dist: fsspec[s3]>=2023.6.0; extra == "remote-s3"
Provides-Extra: remote-gcs
Requires-Dist: fsspec[gcs]>=2023.6.0; extra == "remote-gcs"
Provides-Extra: remote-azure
Requires-Dist: adlfs>=2023.6.0; extra == "remote-azure"
Provides-Extra: remote-sftp
Requires-Dist: fsspec[sftp]>=2023.6.0; extra == "remote-sftp"
Dynamic: license-file
